pyramid_sqlalchemy_sessions/__init__.py
pyramid_sqlalchemy_sessions/authn.py
pyramid_sqlalchemy_sessions/events.py
pyramid_sqlalchemy_sessions/exceptions.py
pyramid_sqlalchemy_sessions/gc.py
pyramid_sqlalchemy_sessions/model.py
pyramid_sqlalchemy_sessions/serializer.py
pyramid_sqlalchemy_sessions/session.py
pyramid_sqlalchemy_sessions/util.py
pyramid_sqlalchemy_sessions-0.1.0.dist-info/DESCRIPTION.rst
pyramid_sqlalchemy_sessions-0.1.0.dist-info/METADATA
pyramid_sqlalchemy_sessions-0.1.0.dist-info/RECORD
pyramid_sqlalchemy_sessions-0.1.0.dist-info/WHEEL
pyramid_sqlalchemy_sessions-0.1.0.dist-info/entry_points.txt
pyramid_sqlalchemy_sessions-0.1.0.dist-info/metadata.json
pyramid_sqlalchemy_sessions-0.1.0.dist-info/top_level.txt
